brightml/__init__.py
brightml/__init___flymake.py
brightml/__main__.py
brightml/battery.py
brightml/brightml.py
brightml/brightness.py
brightml/client.py
brightml/features.py
brightml/file_watcher.py
brightml/notifier.py
brightml/pipeline.py
brightml/scrolling.py
brightml/server.py
brightml/timer.py
brightml/utils.py
brightml/validate.py
brightml/write_brightness.py
brightml/xdisplay.py
brightml-0.2.11.dist-info/LICENSE
brightml-0.2.11.dist-info/METADATA
brightml-0.2.11.dist-info/WHEEL
brightml-0.2.11.dist-info/entry_points.txt
brightml-0.2.11.dist-info/top_level.txt
brightml-0.2.11.dist-info/RECORD
