Metadata-Version: 2.1
Name: brightml
Version: 0.2.11
Summary: Machine Learned Auto brightness
Home-page: https://github.com/kootenpv/brightml
Author: Pascal van Kooten
Author-email: kootenpv@gmail.com
License: MIT
Platform: UNKNOWN
Classifier: Programming Language :: Python
Classifier: Programming Language :: Python :: 2.6
Classifier: Programming Language :: Python :: 2.7
Classifier: Programming Language :: Python :: 3
Classifier: Programming Language :: Python :: 3.3
Classifier: Programming Language :: Python :: 3.4
Classifier: Programming Language :: Python :: 3.5
Classifier: Programming Language :: Python :: 3.6
Classifier: Programming Language :: Python :: Implementation :: CPython
Classifier: Programming Language :: Python :: Implementation :: PyPy
Requires-Dist: scipy
Requires-Dist: numpy
Requires-Dist: pandas
Requires-Dist: scikit-learn
Requires-Dist: python-xlib
Requires-Dist: Pillow
Requires-Dist: simplejson
Requires-Dist: pyinotify
Requires-Dist: watchdog
Requires-Dist: cachetools
Requires-Dist: pynput
Provides-Extra: whereami
Requires-Dist: whereami ; extra == 'whereami'
